zimran/logging/__init__.py
zimran/logging/exceptions.py
zimran/logging/utils.py
zimran_logging-1.2.2.dist-info/METADATA
zimran_logging-1.2.2.dist-info/WHEEL
zimran_logging-1.2.2.dist-info/top_level.txt
zimran_logging-1.2.2.dist-info/RECORD
