Metadata-Version: 2.1
Name: zimran-logging
Version: 1.2.2
Summary: Loguru, Sentry based logging for FastAPI services
Requires-Python: >=3.10
Requires-Dist: loguru
Requires-Dist: sentry-sdk[fastapi,loguru]
